{
	"assets": "./assets",
	"hello": "Hello, Smarty!!",
	"today": "2021/11/18",
	"animal": [
		"うさぎ",
		"ねこ",
		"いぬ"
	],
	"is_enable_async_cart_in_pc": true,
	"view_cart_with_async_info": true,
	"incart_total_count": 10,
	"shop_name": "ショップのタイトル",
	"home_url": "./",
	"logo": "https://img21.shop-pro.jp/PA01437/442/etc/Logo_Black.png",
	"e_copyright": "コピーライト",
	"cart_url": "https://www.saga-ishimaru.co.jp/cart/proxy/basket/items/add",
	"view_cart_url": "「カートを見る」のURL",
	"view_inq_url": "「お問合せ」のURL",
	"view_myaccount_url": "「マイアカウント」のURL",
	"mailmaga_url": "「メルマガ登録・解除」のURL",
	"members_login_url": "「会員専用ページログイン・ログアウト」のURL",
	"members_regi_url": "「新規会員登録」のURL",
	"product_search_url": "「商品検索」のURL",
	"product_search_mode": "「商品検索」のモード",
	"rss_url": "「RSS」のURL",
	"atom_url": "「ATOM」のURL",
	"sk_url": "「特定商取引法」のURL",
	"delivery_url": "「配送方法」のURL",
	"payment_url": "「お支払方法」のURL",
	"privacy_url": "「プライバシーポリシー」のURL",
	"shop_stop_flg": false,
	"members_register_flg": true,
	"members_use_flg": true,
	"members_login_flg": true,
	"members_login_name": "大野洋平",
	"members_id": "123456789",
	"shoppoint_use_flg": false,
	"manager_img": "店長画像URL",
	"manager_name": "店長の名前",
	"manager_url": "店長ブログURL",
	"manager_memo": "店長からのコメント",
	"twitter_url": "Twitterアカウント",
	"instagram_url": "Instagramアカウント",
	"facebook_url": "Facebookアカウント",
	"youtube_url": "Youtubeアカウント",
	"free_area_flg": true,
	"current_freepage_title": "表示されているフリーページの名前",
	"free1_link": "フリーページ１のURL",
	"free1_title": "フリーページ１のタイトル",
	"free2_link": "フリーページ２のURL",
	"free2_title": "フリーページ２のタイトル",
	"free3_link": "フリーページ３のURL",
	"free3_title": "フリーページ３のタイトル",
	"free4_link": "フリーページ４のURL",
	"free4_title": "フリーページ４のタイトル",
	"free5_link": "フリーページ５のURL",
	"free5_title": "フリーページ５のタイトル",
	"free6_link": "フリーページ６のURL",
	"free6_title": "フリーページ６のタイトル",
	"free7_link": "フリーページ７のURL",
	"free7_title": "フリーページ７のタイトル",
	"free8_link": "フリーページ８のURL",
	"free8_title": "フリーページ８のタイトル",
	"free9_link": "フリーページ９のURL",
	"free9_title": "フリーページ９のタイトル",
	"free10_link": "フリーページ１０のURL",
	"free10_title": "フリーページ１０のタイトル",
	"freepage": [
		{
			"link_url": "フリーページ１のURL",
			"page_title": "フリーページ１のタイトル"
		},
		{
			"link_url": "フリーページ2のURL",
			"page_title": "フリーページ2のタイトル"
		},
		{
			"link_url": "フリーページ3のURL",
			"page_title": "フリーページ3のタイトル"
		},
		{
			"link_url": "フリーページ4のURL",
			"page_title": "フリーページ4のタイトル"
		},
		{
			"link_url": "フリーページ5のURL",
			"page_title": "フリーページ5のタイトル"
		},
		{
			"link_url": "フリーページ6のURL",
			"page_title": "フリーページ6のタイトル"
		},
		{
			"link_url": "フリーページ7のURL",
			"page_title": "フリーページ7のタイトル"
		},
		{
			"link_url": "フリーページ8のURL",
			"page_title": "フリーページ8のタイトル"
		},
		{
			"link_url": "フリーページ9のURL",
			"page_title": "フリーページ9のタイトル"
		},
		{
			"link_url": "フリーページ10のURL",
			"page_title": "フリーページ10のタイトル"
		}
	],
	"bid_link": "大カテゴリーURL、またはグループURL（グループ別商品一覧ページ表示時）",
	"bid_name": "大カテゴリー名称、またはグループ名称（グループ別商品一覧ページ表示時）",
	"sid_link": "小カテゴリーURL",
	"sid_name": "小カテゴリー名称",
	"product_link": "商品URL",
	"product_name": "商品名称",
	"category": [
		{
			"bid": 2543763,
			"link_url": "カテゴリー1別商品一覧のURL",
			"img_url": "カテゴリー1画像のURL",
			"name": "佐賀牛"
		},
		{
			"bid": 2547504,
			"link_url": "カテゴリー2別商品一覧のURL",
			"img_url": "カテゴリー2画像のURL",
			"name": "九州産黒毛和牛"
		},
		{
			"bid": 2601547,
			"link_url": "カテゴリー3別商品一覧のURL",
			"img_url": "カテゴリー3画像のURL",
			"name": "その他"
		}
	],
	"group": [
		{
			"id": "2373403",
			"link_url": "https://www.saga-ishimaru.co.jp/?mode=grp&gid=2373403",
			"img_url": "https://img07.shop-pro.jp/PA01437/442/etc/neo-steak-pc.png?cmsp_timestamp=20211129192547",
			"name": "ステーキ"
		},
		{
			"id": "2338001",
			"link_url": "https://www.saga-ishimaru.co.jp/?mode=grp&gid=2338001",
			"img_url": "https://img07.shop-pro.jp/PA01437/442/etc/neo-yakiniku-pc.png?cmsp_timestamp=20211129192559",
			"name": "焼肉"
		},
		{
			"id": "2338000",
			"link_url": "https://www.saga-ishimaru.co.jp/?mode=grp&gid=2338000",
			"img_url": "https://img07.shop-pro.jp/PA01437/442/etc/neo-nabe-pc.png?cmsp_timestamp=20211129192527",
			"name": "しゃぶしゃぶ・すき焼き"
		},
		{
			"id": "2337958",
			"link_url": "https://www.saga-ishimaru.co.jp/?mode=grp&gid=2337958",
			"img_url": "https://img07.shop-pro.jp/PA01437/442/etc/neo-hmbg-pc.png?cmsp_timestamp=20211129192449",
			"name": "ハンバーグ"
		},
		{
			"id": "2337960",
			"link_url": "https://www.saga-ishimaru.co.jp/?mode=grp&gid=2337960",
			"img_url": "",
			"name": "ヒレ"
		},
		{
			"id": "2337981",
			"link_url": "https://www.saga-ishimaru.co.jp/?mode=grp&gid=2337981",
			"img_url": "",
			"name": "ロース"
		},
		{
			"id": "2337986",
			"link_url": "https://www.saga-ishimaru.co.jp/?mode=grp&gid=2337986",
			"img_url": "",
			"name": "小間切れ"
		},
		{
			"id": "2337988",
			"link_url": "https://www.saga-ishimaru.co.jp/?mode=grp&gid=2337988",
			"img_url": "",
			"name": "赤身"
		},
		{
			"id": "2337989",
			"link_url": "https://www.saga-ishimaru.co.jp/?mode=grp&gid=2337958",
			"img_url": "",
			"name": "ウデ"
		},
		{
			"id": "2337999",
			"link_url": "https://www.saga-ishimaru.co.jp/?mode=grp&gid=2337999",
			"img_url": "",
			"name": "モモ"
		},
		{
			"id": "2483504",
			"link_url": "https://www.saga-ishimaru.co.jp/?mode=grp&gid=2337958",
			"img_url": "https://img07.shop-pro.jp/PA01437/442/etc/neo-hmbg-pc.png?cmsp_timestamp=20211129192449",
			"name": "お歳暮特価品"
		},
		{
			"id": "2409217",
			"link_url": "https://www.saga-ishimaru.co.jp/?mode=grp&gid=2409217",
			"img_url": "https://img07.shop-pro.jp/PA01437/442/etc/neo-hmbg-pc.png?cmsp_timestamp=20211129192449",
			"name": "お中元特集"
		},
		{
			"id": "2673106",
			"link_url": "https://www.saga-ishimaru.co.jp/?mode=grp&gid=2673106",
			"img_url": "",
			"name": "～4,999円"
		},
		{
			"id": "2673107",
			"link_url": "https://www.saga-ishimaru.co.jp/?mode=grp&gid=2673107",
			"img_url": "",
			"name": "5,000円～9,999円"
		},
		{
			"id": "2673108",
			"link_url": "https://www.saga-ishimaru.co.jp/?mode=grp&gid=2673108",
			"img_url": "",
			"name": "10,000円～"
		}
	],
	"incart": [
		{
			"id": "商品1ID",
			"name": "商品1名",
			"link_url": "商品1詳細ページのURL",
			"product_num": "数量"
		},
		{
			"id": "商品2ID",
			"name": "商品2名",
			"link_url": "商品2詳細ページのURL",
			"product_num": "数量"
		},
		{
			"id": "商品3ID",
			"name": "商品3名",
			"link_url": "商品3詳細ページのURL",
			"product_num": "数量"
		}
	],
	"recommend_num": "おすすめ商品個数",
	"recommend": [
		{
			"id": "146272783",
			"model": "",
			"name": "【九州産黒毛和牛】 ヒレステーキ600g(120g×5枚)",
			"cut_name": "【九州産黒毛和牛】 ヒレステー",
			"teika": "",
			"teika_disp": false,
			"price": 18800,
			"regular_price": 18800,
			"members_price": 18800,
			"discount_flg": false,
			"discount_rate": "",
			"shoppoint": "100",
			"link_url": "./?p=product",
			"img_url": "https://img07.shop-pro.jp/PA01437/442/product/146272783_th.jpg",
			"large_img_url": "https://img07.shop-pro.jp/PA01437/442/product/146272783.jpg",
			"soldout_flg": 0,
			"s_expl": "商品簡易説明",
			"option_price": {
				"max": 19300,
				"min": 18800,
				"max_regular": 19300,
				"min_regular": 18800,
				"max_members": 19300,
				"min_members": 18800
			}
		},
		{
			"id": "146272783",
			"model": "",
			"name": "【九州産黒毛和牛】 ヒレステーキ600g(120g×5枚)",
			"cut_name": "【九州産黒毛和牛】 ヒレステー",
			"teika": "",
			"teika_disp": false,
			"price": 18800,
			"regular_price": 18800,
			"members_price": 18800,
			"discount_flg": false,
			"discount_rate": "",
			"shoppoint": "100",
			"link_url": "./?p=product",
			"img_url": "https://img07.shop-pro.jp/PA01437/442/product/146272783_th.jpg",
			"large_img_url": "https://img07.shop-pro.jp/PA01437/442/product/146272783.jpg",
			"soldout_flg": 0,
			"s_expl": "商品簡易説明",
			"option_price": {
				"max": 19300,
				"min": 18800,
				"max_regular": 19300,
				"min_regular": 18800,
				"max_members": 19300,
				"min_members": 18800
			}
		},
		{
			"id": "146272783",
			"model": "",
			"name": "【九州産黒毛和牛】 ヒレステーキ600g(120g×5枚)",
			"cut_name": "【九州産黒毛和牛】 ヒレステー",
			"teika": "",
			"teika_disp": false,
			"price": 18800,
			"regular_price": 18800,
			"members_price": 18800,
			"discount_flg": false,
			"discount_rate": "",
			"shoppoint": "100",
			"link_url": "./?p=product",
			"img_url": "https://img07.shop-pro.jp/PA01437/442/product/146272783_th.jpg",
			"large_img_url": "https://img07.shop-pro.jp/PA01437/442/product/146272783.jpg",
			"soldout_flg": 0,
			"s_expl": "商品簡易説明",
			"option_price": {
				"max": 19300,
				"min": 18800,
				"max_regular": 19300,
				"min_regular": 18800,
				"max_members": 19300,
				"min_members": 18800
			}
		},
		{
			"id": "146272783",
			"model": "",
			"name": "【九州産黒毛和牛】 ヒレステーキ600g(120g×5枚)",
			"cut_name": "【九州産黒毛和牛】 ヒレステー",
			"teika": "",
			"teika_disp": false,
			"price": 18800,
			"regular_price": 18800,
			"members_price": 18800,
			"discount_flg": false,
			"discount_rate": "",
			"shoppoint": "100",
			"link_url": "./?p=product",
			"img_url": "https://img07.shop-pro.jp/PA01437/442/product/146272783_th.jpg",
			"large_img_url": "https://img07.shop-pro.jp/PA01437/442/product/146272783.jpg",
			"soldout_flg": 0,
			"s_expl": "商品簡易説明",
			"option_price": {
				"max": 19300,
				"min": 18800,
				"max_regular": 19300,
				"min_regular": 18800,
				"max_members": 19300,
				"min_members": 18800
			}
		},
		{
			"id": "146272783",
			"model": "",
			"name": "【九州産黒毛和牛】 ヒレステーキ600g(120g×5枚)",
			"cut_name": "【九州産黒毛和牛】 ヒレステー",
			"teika": "",
			"teika_disp": false,
			"price": 18800,
			"regular_price": 18800,
			"members_price": 18800,
			"discount_flg": false,
			"discount_rate": "",
			"shoppoint": "100",
			"link_url": "./?p=product",
			"img_url": "https://img07.shop-pro.jp/PA01437/442/product/146272783_th.jpg",
			"large_img_url": "https://img07.shop-pro.jp/PA01437/442/product/146272783.jpg",
			"soldout_flg": 0,
			"s_expl": "商品簡易説明",
			"option_price": {
				"max": 19300,
				"min": 18800,
				"max_regular": 19300,
				"min_regular": 18800,
				"max_members": 19300,
				"min_members": 18800
			}
		}
	],
	"seller_num": "売れ筋商品個数",
	"seller": [
		{
			"id": "146272783",
			"model": "",
			"name": "【九州産黒毛和牛】 ヒレステーキ600g(120g×5枚)",
			"cut_name": "【九州産黒毛和牛】 ヒレステー",
			"teika": "",
			"teika_disp": false,
			"price": 18800,
			"regular_price": 18800,
			"members_price": 18800,
			"discount_flg": false,
			"discount_rate": "",
			"shoppoint": "100",
			"link_url": "./?p=product",
			"img_url": "https://img07.shop-pro.jp/PA01437/442/product/146272783_th.jpg",
			"large_img_url": "https://img07.shop-pro.jp/PA01437/442/product/146272783.jpg",
			"soldout_flg": 0,
			"s_expl": "商品簡易説明",
			"option_price": {
				"max": 19300,
				"min": 18800,
				"max_regular": 19300,
				"min_regular": 18800,
				"max_members": 19300,
				"min_members": 18800
			}
		},
		{
			"id": "146272783",
			"model": "",
			"name": "【九州産黒毛和牛】 ヒレステーキ600g(120g×5枚)",
			"cut_name": "【九州産黒毛和牛】 ヒレステー",
			"teika": "",
			"teika_disp": false,
			"price": 18800,
			"regular_price": 18800,
			"members_price": 18800,
			"discount_flg": false,
			"discount_rate": "",
			"shoppoint": "100",
			"link_url": "./?p=product",
			"img_url": "https://img07.shop-pro.jp/PA01437/442/product/146272783_th.jpg",
			"large_img_url": "https://img07.shop-pro.jp/PA01437/442/product/146272783.jpg",
			"soldout_flg": 0,
			"s_expl": "商品簡易説明",
			"option_price": {
				"max": 19300,
				"min": 18800,
				"max_regular": 19300,
				"min_regular": 18800,
				"max_members": 19300,
				"min_members": 18800
			}
		},
		{
			"id": "146272783",
			"model": "",
			"name": "【九州産黒毛和牛】 ヒレステーキ600g(120g×5枚)",
			"cut_name": "【九州産黒毛和牛】 ヒレステー",
			"teika": "",
			"teika_disp": false,
			"price": 18800,
			"regular_price": 18800,
			"members_price": 18800,
			"discount_flg": false,
			"discount_rate": "",
			"shoppoint": "100",
			"link_url": "./?p=product",
			"img_url": "https://img07.shop-pro.jp/PA01437/442/product/146272783_th.jpg",
			"large_img_url": "https://img07.shop-pro.jp/PA01437/442/product/146272783.jpg",
			"soldout_flg": 0,
			"s_expl": "商品簡易説明",
			"option_price": {
				"max": 19300,
				"min": 18800,
				"max_regular": 19300,
				"min_regular": 18800,
				"max_members": 19300,
				"min_members": 18800
			}
		},
		{
			"id": "146272783",
			"model": "",
			"name": "【九州産黒毛和牛】 ヒレステーキ600g(120g×5枚)",
			"cut_name": "【九州産黒毛和牛】 ヒレステー",
			"teika": "",
			"teika_disp": false,
			"price": 18800,
			"regular_price": 18800,
			"members_price": 18800,
			"discount_flg": false,
			"discount_rate": "",
			"shoppoint": "100",
			"link_url": "./?p=product",
			"img_url": "https://img07.shop-pro.jp/PA01437/442/product/146272783_th.jpg",
			"large_img_url": "https://img07.shop-pro.jp/PA01437/442/product/146272783.jpg",
			"soldout_flg": 0,
			"s_expl": "商品簡易説明",
			"option_price": {
				"max": 19300,
				"min": 18800,
				"max_regular": 19300,
				"min_regular": 18800,
				"max_members": 19300,
				"min_members": 18800
			}
		},
		{
			"id": "146272783",
			"model": "",
			"name": "【九州産黒毛和牛】 ヒレステーキ600g(120g×5枚)",
			"cut_name": "【九州産黒毛和牛】 ヒレステー",
			"teika": "",
			"teika_disp": false,
			"price": 18800,
			"regular_price": 18800,
			"members_price": 18800,
			"discount_flg": false,
			"discount_rate": "",
			"shoppoint": "100",
			"link_url": "./?p=product",
			"img_url": "https://img07.shop-pro.jp/PA01437/442/product/146272783_th.jpg",
			"large_img_url": "https://img07.shop-pro.jp/PA01437/442/product/146272783.jpg",
			"soldout_flg": 0,
			"s_expl": "商品簡易説明",
			"option_price": {
				"max": 19300,
				"min": 18800,
				"max_regular": 19300,
				"min_regular": 18800,
				"max_members": 19300,
				"min_members": 18800
			}
		}
	],
	"shop": {
		"shop_name": "販売業者",
		"manager_name": "運営統括責任者名",
		"postal": "郵便番号",
		"address": "住所",
		"price": "商品代金以外の料金の説明",
		"apply_limit": "申込有効期限",
		"bad_product": "不良品",
		"sales_num": "販売数量",
		"delivery_time": "引渡し時期",
		"payment_way": "お支払方法",
		"payment_limit": "お支払期限",
		"return_limit": "返品期限",
		"return_price": "返品送料",
		"license": "資格･免許",
		"service_name": "屋号またはサービス名",
		"tel": "電話番号",
		"email": "公開メールアドレス",
		"hp_address": "ホームページアドレス"
	},
	"sk_payment": [
		{
			"name": "決済名称",
			"img_url": "画像URL",
			"card_img": "カードイメージ",
			"fee_str": "（未使用）",
			"other": "備考"
		},
		{
			"name": "決済名称",
			"img_url": "画像URL",
			"card_img": "カードイメージ",
			"fee_str": "（未使用）",
			"other": "備考"
		},
		{
			"name": "決済名称",
			"img_url": "画像URL",
			"card_img": "カードイメージ",
			"fee_str": "（未使用）",
			"other": "備考"
		}
	],
	"sk_delivery": [
		{
			"name": "配送方法名称",
			"img_url": "画像URL",
			"other": "備考"
		},
		{
			"name": "配送方法名称",
			"img_url": "画像URL",
			"other": "備考"
		},
		{
			"name": "配送方法名称",
			"img_url": "画像URL",
			"other": "備考"
		}
	],
	"paperboy_url": "弊社HPのURL",
	"paperboy_name": "弊社の社名",
	"paperboy_privacy_url": "弊社プライバシーポリシーへのリンクURL",
	"cmsp_url": "「カラーミーショップ」HPへのリンク",
	"cmsp_name": "「カラーミーショップ」のサービス名",
	"view_smartphone_url": "スマートフォンショップへのリンクURL　※2011/05/19追加",
	"PC_IMAGES_PATH": "PC版テンプレートで使用されている画像ディレクトリのURL※2012/04/25追加",
	"SMART_IMAGES_PATH": "スマートフォン版テンプレートで使用されている画像ディレクトリのURL※2012/04/25追加",
	"MOBILE_IMAGES_PATH": "携帯版テンプレートで使用されている画像ディレクトリのURL※2012/04/25追加",
	"history_num": "新着商品個数",
	"history": [
		{
			"id": "146272783",
			"model": "",
			"name": "【九州産黒毛和牛】 ヒレステーキ600g(120g×5枚)",
			"cut_name": "【九州産黒毛和牛】 ヒレステー",
			"teika": "",
			"teika_disp": false,
			"price": 18800,
			"regular_price": 18800,
			"members_price": 18800,
			"discount_flg": false,
			"discount_rate": "",
			"shoppoint": "100",
			"link_url": "./?p=product",
			"img_url": "https://img07.shop-pro.jp/PA01437/442/product/146272783_th.jpg",
			"large_img_url": "https://img07.shop-pro.jp/PA01437/442/product/146272783.jpg",
			"soldout_flg": 0,
			"s_expl": "商品簡易説明",
			"option_price": {
				"max": 19300,
				"min": 18800,
				"max_regular": 19300,
				"min_regular": 18800,
				"max_members": 19300,
				"min_members": 18800
			}
		},
		{
			"id": "146272783",
			"model": "",
			"name": "【九州産黒毛和牛】 ヒレステーキ600g(120g×5枚)",
			"cut_name": "【九州産黒毛和牛】 ヒレステー",
			"teika": "",
			"teika_disp": false,
			"price": 18800,
			"regular_price": 18800,
			"members_price": 18800,
			"discount_flg": false,
			"discount_rate": "",
			"shoppoint": "100",
			"link_url": "./?p=product",
			"img_url": "https://img07.shop-pro.jp/PA01437/442/product/146272783_th.jpg",
			"large_img_url": "https://img07.shop-pro.jp/PA01437/442/product/146272783.jpg",
			"soldout_flg": 0,
			"s_expl": "商品簡易説明",
			"option_price": {
				"max": 19300,
				"min": 18800,
				"max_regular": 19300,
				"min_regular": 18800,
				"max_members": 19300,
				"min_members": 18800
			}
		},
		{
			"id": "146272783",
			"model": "",
			"name": "【九州産黒毛和牛】 ヒレステーキ600g(120g×5枚)",
			"cut_name": "【九州産黒毛和牛】 ヒレステー",
			"teika": "",
			"teika_disp": false,
			"price": 18800,
			"regular_price": 18800,
			"members_price": 18800,
			"discount_flg": false,
			"discount_rate": "",
			"shoppoint": "100",
			"link_url": "./?p=product",
			"img_url": "https://img07.shop-pro.jp/PA01437/442/product/146272783_th.jpg",
			"large_img_url": "https://img07.shop-pro.jp/PA01437/442/product/146272783.jpg",
			"soldout_flg": 0,
			"s_expl": "商品簡易説明",
			"option_price": {
				"max": 19300,
				"min": 18800,
				"max_regular": 19300,
				"min_regular": 18800,
				"max_members": 19300,
				"min_members": 18800
			}
		},
		{
			"id": "146272783",
			"model": "",
			"name": "【九州産黒毛和牛】 ヒレステーキ600g(120g×5枚)",
			"cut_name": "【九州産黒毛和牛】 ヒレステー",
			"teika": "",
			"teika_disp": false,
			"price": 18800,
			"regular_price": 18800,
			"members_price": 18800,
			"discount_flg": false,
			"discount_rate": "",
			"shoppoint": "100",
			"link_url": "./?p=product",
			"img_url": "https://img07.shop-pro.jp/PA01437/442/product/146272783_th.jpg",
			"large_img_url": "https://img07.shop-pro.jp/PA01437/442/product/146272783.jpg",
			"soldout_flg": 0,
			"s_expl": "商品簡易説明",
			"option_price": {
				"max": 19300,
				"min": 18800,
				"max_regular": 19300,
				"min_regular": 18800,
				"max_members": 19300,
				"min_members": 18800
			}
		},
		{
			"id": "146272783",
			"model": "",
			"name": "【九州産黒毛和牛】 ヒレステーキ600g(120g×5枚)",
			"cut_name": "【九州産黒毛和牛】 ヒレステー",
			"teika": "",
			"teika_disp": false,
			"price": 18800,
			"regular_price": 18800,
			"members_price": 18800,
			"discount_flg": false,
			"discount_rate": "",
			"shoppoint": "100",
			"link_url": "./?p=product",
			"img_url": "https://img07.shop-pro.jp/PA01437/442/product/146272783_th.jpg",
			"large_img_url": "https://img07.shop-pro.jp/PA01437/442/product/146272783.jpg",
			"soldout_flg": 0,
			"s_expl": "商品簡易説明",
			"option_price": {
				"max": 19300,
				"min": 18800,
				"max_regular": 19300,
				"min_regular": 18800,
				"max_members": 19300,
				"min_members": 18800
			}
		}
	],
	"favorite_button_attribute": "お気に入りボタン",
	"favorite_num": "お気に入り商品個数",
	"favorite": [
		{
			"id": "146272783",
			"model": "",
			"name": "【九州産黒毛和牛】 ヒレステーキ600g(120g×5枚)",
			"cut_name": "【九州産黒毛和牛】 ヒレステー",
			"teika": "",
			"teika_disp": false,
			"price": 18800,
			"regular_price": 18800,
			"members_price": 18800,
			"discount_flg": false,
			"discount_rate": "",
			"shoppoint": "100",
			"link_url": "./?p=product",
			"img_url": "https://img07.shop-pro.jp/PA01437/442/product/146272783_th.jpg",
			"large_img_url": "https://img07.shop-pro.jp/PA01437/442/product/146272783.jpg",
			"soldout_flg": 0,
			"s_expl": "商品簡易説明",
			"option_price": {
				"max": 19300,
				"min": 18800,
				"max_regular": 19300,
				"min_regular": 18800,
				"max_members": 19300,
				"min_members": 18800
			}
		},
		{
			"id": "146272783",
			"model": "",
			"name": "【九州産黒毛和牛】 ヒレステーキ600g(120g×5枚)",
			"cut_name": "【九州産黒毛和牛】 ヒレステー",
			"teika": "",
			"teika_disp": false,
			"price": 18800,
			"regular_price": 18800,
			"members_price": 18800,
			"discount_flg": false,
			"discount_rate": "",
			"shoppoint": "100",
			"link_url": "./?p=product",
			"img_url": "https://img07.shop-pro.jp/PA01437/442/product/146272783_th.jpg",
			"large_img_url": "https://img07.shop-pro.jp/PA01437/442/product/146272783.jpg",
			"soldout_flg": 0,
			"s_expl": "商品簡易説明",
			"option_price": {
				"max": 19300,
				"min": 18800,
				"max_regular": 19300,
				"min_regular": 18800,
				"max_members": 19300,
				"min_members": 18800
			}
		},
		{
			"id": "146272783",
			"model": "",
			"name": "【九州産黒毛和牛】 ヒレステーキ600g(120g×5枚)",
			"cut_name": "【九州産黒毛和牛】 ヒレステー",
			"teika": "",
			"teika_disp": false,
			"price": 18800,
			"regular_price": 18800,
			"members_price": 18800,
			"discount_flg": false,
			"discount_rate": "",
			"shoppoint": "100",
			"link_url": "./?p=product",
			"img_url": "https://img07.shop-pro.jp/PA01437/442/product/146272783_th.jpg",
			"large_img_url": "https://img07.shop-pro.jp/PA01437/442/product/146272783.jpg",
			"soldout_flg": 0,
			"s_expl": "商品簡易説明",
			"option_price": {
				"max": 19300,
				"min": 18800,
				"max_regular": 19300,
				"min_regular": 18800,
				"max_members": 19300,
				"min_members": 18800
			}
		},
		{
			"id": "146272783",
			"model": "",
			"name": "【九州産黒毛和牛】 ヒレステーキ600g(120g×5枚)",
			"cut_name": "【九州産黒毛和牛】 ヒレステー",
			"teika": "",
			"teika_disp": false,
			"price": 18800,
			"regular_price": 18800,
			"members_price": 18800,
			"discount_flg": false,
			"discount_rate": "",
			"shoppoint": "100",
			"link_url": "./?p=product",
			"img_url": "https://img07.shop-pro.jp/PA01437/442/product/146272783_th.jpg",
			"large_img_url": "https://img07.shop-pro.jp/PA01437/442/product/146272783.jpg",
			"soldout_flg": 0,
			"s_expl": "商品簡易説明",
			"option_price": {
				"max": 19300,
				"min": 18800,
				"max_regular": 19300,
				"min_regular": 18800,
				"max_members": 19300,
				"min_members": 18800
			}
		}
	],
	"info": "インフォメーション",
	"free_space": "フリースペース",
	"eyecatch": "トップページバナー",
	"calendar": "営業日カレンダー",
	"calendar_memo": "注意書き",
	"news": [
		{
			"date": "公開日付",
			"link_url": "設定しているURL",
			"message": "お知らせの内容"
		},
		{
			"date": "公開日付",
			"link_url": "設定しているURL",
			"message": "お知らせの内容"
		},
		{
			"date": "公開日付",
			"link_url": "設定しているURL",
			"message": "お知らせの内容"
		},
		{
			"date": "公開日付",
			"link_url": "設定しているURL",
			"message": "お知らせの内容"
		}
	],
	"new_item_num": "新着商品個数",
	"new_item": [
		{
			"id": "146272783",
			"model": "",
			"name": "【九州産黒毛和牛】 ヒレステーキ600g(120g×5枚)",
			"cut_name": "【九州産黒毛和牛】 ヒレステー",
			"teika": "",
			"teika_disp": false,
			"price": 18800,
			"regular_price": 18800,
			"members_price": 18800,
			"discount_flg": false,
			"discount_rate": "",
			"shoppoint": "100",
			"link_url": "./?p=product",
			"img_url": "https://img07.shop-pro.jp/PA01437/442/product/146272783_th.jpg",
			"large_img_url": "https://img07.shop-pro.jp/PA01437/442/product/146272783.jpg",
			"soldout_flg": 0,
			"s_expl": "商品簡易説明",
			"option_price": {
				"max": 19300,
				"min": 18800,
				"max_regular": 19300,
				"min_regular": 18800,
				"max_members": 19300,
				"min_members": 18800
			}
		},
		{
			"id": "146272783",
			"model": "",
			"name": "【九州産黒毛和牛】 ヒレステーキ600g(120g×5枚)",
			"cut_name": "【九州産黒毛和牛】 ヒレステー",
			"teika": "",
			"teika_disp": false,
			"price": 18800,
			"regular_price": 18800,
			"members_price": 18800,
			"discount_flg": false,
			"discount_rate": "",
			"shoppoint": "100",
			"link_url": "./?p=product",
			"img_url": "https://img07.shop-pro.jp/PA01437/442/product/146272783_th.jpg",
			"large_img_url": "https://img07.shop-pro.jp/PA01437/442/product/146272783.jpg",
			"soldout_flg": 0,
			"s_expl": "商品簡易説明",
			"option_price": {
				"max": 19300,
				"min": 18800,
				"max_regular": 19300,
				"min_regular": 18800,
				"max_members": 19300,
				"min_members": 18800
			}
		},
		{
			"id": "146272783",
			"model": "",
			"name": "【九州産黒毛和牛】 ヒレステーキ600g(120g×5枚)",
			"cut_name": "【九州産黒毛和牛】 ヒレステー",
			"teika": "",
			"teika_disp": false,
			"price": 18800,
			"regular_price": 18800,
			"members_price": 18800,
			"discount_flg": false,
			"discount_rate": "",
			"shoppoint": "100",
			"link_url": "./?p=product",
			"img_url": "https://img07.shop-pro.jp/PA01437/442/product/146272783_th.jpg",
			"large_img_url": "https://img07.shop-pro.jp/PA01437/442/product/146272783.jpg",
			"soldout_flg": 0,
			"s_expl": "商品簡易説明",
			"option_price": {
				"max": 19300,
				"min": 18800,
				"max_regular": 19300,
				"min_regular": 18800,
				"max_members": 19300,
				"min_members": 18800
			}
		},
		{
			"id": "146272783",
			"model": "",
			"name": "【九州産黒毛和牛】 ヒレステーキ600g(120g×5枚)",
			"cut_name": "【九州産黒毛和牛】 ヒレステー",
			"teika": "",
			"teika_disp": false,
			"price": 18800,
			"regular_price": 18800,
			"members_price": 18800,
			"discount_flg": false,
			"discount_rate": "",
			"shoppoint": "100",
			"link_url": "./?p=product",
			"img_url": "https://img07.shop-pro.jp/PA01437/442/product/146272783_th.jpg",
			"large_img_url": "https://img07.shop-pro.jp/PA01437/442/product/146272783.jpg",
			"soldout_flg": 0,
			"s_expl": "商品簡易説明",
			"option_price": {
				"max": 19300,
				"min": 18800,
				"max_regular": 19300,
				"min_regular": 18800,
				"max_members": 19300,
				"min_members": 18800
			}
		},
		{
			"id": "146272783",
			"model": "",
			"name": "【九州産黒毛和牛】 ヒレステーキ600g(120g×5枚)",
			"cut_name": "【九州産黒毛和牛】 ヒレステー",
			"teika": "",
			"teika_disp": false,
			"price": 18800,
			"regular_price": 18800,
			"members_price": 18800,
			"discount_flg": false,
			"discount_rate": "",
			"shoppoint": "100",
			"link_url": "./?p=product",
			"img_url": "https://img07.shop-pro.jp/PA01437/442/product/146272783_th.jpg",
			"large_img_url": "https://img07.shop-pro.jp/PA01437/442/product/146272783.jpg",
			"soldout_flg": 0,
			"s_expl": "商品簡易説明",
			"option_price": {
				"max": 19300,
				"min": 18800,
				"max_regular": 19300,
				"min_regular": 18800,
				"max_members": 19300,
				"min_members": 18800
			}
		}
	],
	"push_num": "新着商品個数",
	"push": [
		{
			"id": "146272783",
			"model": "",
			"name": "【九州産黒毛和牛】 ヒレステーキ600g(120g×5枚)",
			"cut_name": "【九州産黒毛和牛】 ヒレステー",
			"teika": "",
			"teika_disp": false,
			"price": 18800,
			"regular_price": 18800,
			"members_price": 18800,
			"discount_flg": false,
			"discount_rate": "",
			"shoppoint": "100",
			"link_url": "./?p=product",
			"img_url": "https://img07.shop-pro.jp/PA01437/442/product/146272783_th.jpg",
			"large_img_url": "https://img07.shop-pro.jp/PA01437/442/product/146272783.jpg",
			"soldout_flg": 0,
			"s_expl": "商品簡易説明",
			"option_price": {
				"max": 19300,
				"min": 18800,
				"max_regular": 19300,
				"min_regular": 18800,
				"max_members": 19300,
				"min_members": 18800
			}
		},
		{
			"id": "146272783",
			"model": "",
			"name": "【九州産黒毛和牛】 ヒレステーキ600g(120g×5枚)",
			"cut_name": "【九州産黒毛和牛】 ヒレステー",
			"teika": "",
			"teika_disp": false,
			"price": 18800,
			"regular_price": 18800,
			"members_price": 18800,
			"discount_flg": false,
			"discount_rate": "",
			"shoppoint": "100",
			"link_url": "./?p=product",
			"img_url": "https://img07.shop-pro.jp/PA01437/442/product/146272783_th.jpg",
			"large_img_url": "https://img07.shop-pro.jp/PA01437/442/product/146272783.jpg",
			"soldout_flg": 0,
			"s_expl": "商品簡易説明",
			"option_price": {
				"max": 19300,
				"min": 18800,
				"max_regular": 19300,
				"min_regular": 18800,
				"max_members": 19300,
				"min_members": 18800
			}
		},
		{
			"id": "146272783",
			"model": "",
			"name": "【九州産黒毛和牛】 ヒレステーキ600g(120g×5枚)",
			"cut_name": "【九州産黒毛和牛】 ヒレステー",
			"teika": "",
			"teika_disp": false,
			"price": 18800,
			"regular_price": 18800,
			"members_price": 18800,
			"discount_flg": false,
			"discount_rate": "",
			"shoppoint": "100",
			"link_url": "./?p=product",
			"img_url": "https://img07.shop-pro.jp/PA01437/442/product/146272783_th.jpg",
			"large_img_url": "https://img07.shop-pro.jp/PA01437/442/product/146272783.jpg",
			"soldout_flg": 0,
			"s_expl": "商品簡易説明",
			"option_price": {
				"max": 19300,
				"min": 18800,
				"max_regular": 19300,
				"min_regular": 18800,
				"max_members": 19300,
				"min_members": 18800
			}
		},
		{
			"id": "146272783",
			"model": "",
			"name": "【九州産黒毛和牛】 ヒレステーキ600g(120g×5枚)",
			"cut_name": "【九州産黒毛和牛】 ヒレステー",
			"teika": "",
			"teika_disp": false,
			"price": 18800,
			"regular_price": 18800,
			"members_price": 18800,
			"discount_flg": false,
			"discount_rate": "",
			"shoppoint": "100",
			"link_url": "./?p=product",
			"img_url": "https://img07.shop-pro.jp/PA01437/442/product/146272783_th.jpg",
			"large_img_url": "https://img07.shop-pro.jp/PA01437/442/product/146272783.jpg",
			"soldout_flg": 0,
			"s_expl": "商品簡易説明",
			"option_price": {
				"max": 19300,
				"min": 18800,
				"max_regular": 19300,
				"min_regular": 18800,
				"max_members": 19300,
				"min_members": 18800
			}
		},
		{
			"id": "146272783",
			"model": "",
			"name": "【九州産黒毛和牛】 ヒレステーキ600g(120g×5枚)",
			"cut_name": "【九州産黒毛和牛】 ヒレステー",
			"teika": "",
			"teika_disp": false,
			"price": 18800,
			"regular_price": 18800,
			"members_price": 18800,
			"discount_flg": false,
			"discount_rate": "",
			"shoppoint": "100",
			"link_url": "./?p=product",
			"img_url": "https://img07.shop-pro.jp/PA01437/442/product/146272783_th.jpg",
			"large_img_url": "https://img07.shop-pro.jp/PA01437/442/product/146272783.jpg",
			"soldout_flg": 0,
			"s_expl": "商品簡易説明",
			"option_price": {
				"max": 19300,
				"min": 18800,
				"max_regular": 19300,
				"min_regular": 18800,
				"max_members": 19300,
				"min_members": 18800
			}
		}
	],
	"prod_inq_url": "お問合せリンクURL",
	"prod_teach_url": "この商品を友達に教えるリンクURL",
	"keep_shopping_url": "買い物を続けるのリンクURL",
	"num_button": "数量UP・DOWNボタン",
	"num_up_url": "数量UPボタンのURL",
	"num_dw_url": "数量DOWNボタンのURL",
	"num_up_img_url": "数量UPボタンの画像",
	"num_dw_img_url": "数量DOWNボタンの画像",
	"opt_url": "オプションの在庫・値段表へのリンクURL",
	"easy_order_flg": "クイック購入利用フラグ（クイック購入が利用可能な場合TRUE、それ以外はFALSE）",
	"easy_order_url": "クイック購入URL",
	"product": {
		"id": "146272783",
		"model": "",
		"name": "【九州産黒毛和牛】 ヒレステーキ600g(120g×5枚)",
		"price": "37,600円(税込)",
		"price_disp": true,
		"sales": "18,800円(税込)",
		"regular_price": "37,600円(税込)",
		"members_price": "18,800円(税込)",
		"discount_flg": true,
		"discount_rate": "50%",
		"shoppoint": "100",
		"unit": "",
		"weight": "重量（重量の単位である「g」は出力されません）",
		"stock_disp": "在庫表示フラグ",
		"stock_str": 100,
		"img_url": "https://img07.shop-pro.jp/PA01437/442/product/146272783.jpg",
		"ot1_url": "https://img07.shop-pro.jp/PA01437/442/product/146272783_o1.jpg",
		"ot2_url": "https://img07.shop-pro.jp/PA01437/442/product/146272783_o2.jpg",
		"simple_explain": "やわらかな食感とあふれる肉汁､その味わいは最高級の逸品です。希少部位ヒレ肉のとても柔らかくキメの細かい、口いっぱいに広がる至極の瞬間をご堪能ください。",
		"explain": "<span style=\"font-size:large;\"><strong>\u300a\u3084\u308f\u3089\u304b\u306a\u98df\u611f\uff64\u30b8\u30e5\u30fc\u30b7\u30fc\u306a\u5473\u308f\u3044\u6700\u9ad8\u7d1a\u90e8\u4f4d\u30d2\u30ec\u8089\u306e\u30b9\u30c6\u30fc\u30ad\u300b<\/strong><\/span><br>\n<img src=\"https:\/\/img21.shop-pro.jp\/PA01437\/442\/etc\/resize_2013.jpg?cmsp_timestamp=20191229180200\" alt=\"\"><br style=\"clear:both;\"><br>\n\u9ed2\u6bdb\u548c\u725b1\u982d\u304b\u3089\u6570kg\u3057\u304b\u53d6\u308c\u306a\u3044\u9ad8\u7d1a\u5e0c\u5c11\u90e8\u4f4d\u30d2\u30ec\u8089\u3092\u304a\u5c4a\u3051\u3057\u307e\u3059\u3002<br>\n<br>\n\u3084\u308f\u3089\u304b\u306a\u98df\u611f\u3068\u3042\u3075\u308c\u308b\u8089\u6c41\uff64\u305d\u306e\u5473\u308f\u3044\u306f\u6700\u9ad8\u7d1a\u306e\u9038\u54c1\u3067\u3059\u3002<br>\n\u5e0c\u5c11\u90e8\u4f4d\u30d2\u30ec\u8089\u306e\u3068\u3066\u3082\u67d4\u3089\u304b\u304f\u30ad\u30e1\u306e\u7d30\u304b\u3044\u3001\u53e3\u3044\u3063\u3071\u3044\u306b\u5e83\u304c\u308b\u81f3\u6975\u306e\u77ac\u9593\u3092\u3054\u582a\u80fd\u4e0b\u3055\u3044\u3002<br>\n<br>\n<span style=\"font-size:large;\"><strong>\u300a\u4e5d\u5dde\u7523\u9ed2\u6bdb\u548c\u725b\u3068\u306f\u300b<\/strong><\/span><br>\n\u4e5d\u5dde\u7523\u9ed2\u6bdb\u548c\u725b\u3068\u306f\u3001\u81ea\u7136\u8c4a\u304b\u306a\u4e5d\u5dde\u3067\u80b2\u3063\u305f\u9ed2\u6bdb\u548c\u725b\u3067\u3059\u3002<br>\n<br>\n<img src=\"https:\/\/img21.shop-pro.jp\/PA01437\/442\/etc\/%A5%B9%A5%C6%A1%BC%A5%AD.jpg?cmsp_timestamp=20191229175745\" alt=\"\"><br>\n<br>\n\u5473\u306f\u3082\u3061\u308d\u3093\u3001\u56fd\u7523\u3067\u5b89\u5fc3\u30fb\u5b89\u5168\u3055\u3082\u9b45\u529b\u306e\u4e00\u3064\u3067\u3059\uff01<br>\n\u4f50\u8cc0\u725b\u306b\u6bd4\u3079\u30ea\u30fc\u30ba\u30ca\u30d6\u30eb\uff01<br>\n<br>\n\u4f50\u8cc0\u725b\u306f\u8102\u304c\u4e57\u308a\u3059\u304e\u3066\u305f\u304f\u3055\u3093\u98df\u3079\u3089\u308c\u306a\u3044\u3068\u3044\u3046\u65b9\u306b\u3082\u4e5d\u5dde\u7523\u9ed2\u6bdb\u548c\u725b\u306f\u304a\u3059\u3059\u3081\u3002<br>\n\u305c\u3072\u3053\u306e\u6a5f\u4f1a\u306b\u300c\u4e5d\u5dde\u7523\u9ed2\u6bdb\u548c\u725b\u300d\u306e\u7f8e\u5473\u3057\u3055\u3092\u304a\u697d\u3057\u307f\u304f\u3060\u3055\u3044\uff01<br>\n<br>\n<span style=\"font-size:large;\"><strong>\u300a\u4f50\u8cc0\u7523\u7389\u306d\u304e\u3092\u4f7f\u7528\u3057\u305f\u7279\u88fd\u304c\u3070\u3044\u30bd\u30fc\u30b9\u306f\u3044\u304b\u304c\u3067\u3059\u304b\uff1f\u300b<\/strong><\/span><br>\n<img src=\"https:\/\/img21.shop-pro.jp\/PA01437\/442\/etc\/resize_9847.jpg?cmsp_timestamp=20200105184441\" alt=\"\"><br>\n<br>\n\u4f50\u8cc0\u7523\u7389\u306d\u304e\u4f7f\u7528\u3057\u305f100\uff05\u7121\u6dfb\u52a0\u306e\u304c\u3070\u3044\u30bd\u30fc\u30b9\u3092\u30bb\u30c3\u30c8\u3092500\u5186(\u7a0e\u8fbc)\u3067\u304a\u4ed8\u3051\u3044\u305f\u3057\u307e\u3059\u3002<br>\n\u4e5d\u5dde\u7523\u9ed2\u6bdb\u548c\u725b\u3068\u304c\u3070\u3044\u30bd\u30fc\u30b9\u306e\u30b3\u30e9\u30dc\u30ec\u30fc\u30b7\u30e7\u30f3\u3092\u662f\u975e\u3054\u582a\u80fd\u4e0b\u3055\u3044\u3002<br>\n<br>\n<span style=\"font-size:large;\">\u25a0\u5185\u5bb9\u91cf\/\u52a0\u5de5\u5730<\/span><br>\n\u30fb\u4f50\u8cc0\u7523\u548c\u725b\u30d2\u30ec\u30b9\u30c6\u30fc\u30ad<br>\n120g\u00d75\u3014600g\u3015<br>\n\u3010\u52a0\u5de5\u5730:\u5168\u3066\u4f50\u8cc0\u770c\u307f\u3084\u304d\u753a\u3011<br>\n<br>\n<span style=\"font-size:large;\">\u25a0\u8cde\u5473\u671f\u9650<\/span><br>\n\u51b7\u51cd\u4fdd\u5b58\u3067\u5168\u306690\u65e5<br>\n<br>\n<span style=\"font-size:large;\">\u25a0\u6ce8\u610f\u4e8b\u9805\/\u305d\u306e\u4ed6<\/span><br>\n\u30fb\u51b7\u51cd\u3067\u306e\u304a\u5c4a\u3051\u3068\u306a\u308a\u307e\u3059\u3002\u304a\u4f7f\u3044\u306b\u306a\u308b\u3068\u304d\u306f\u3001\u51b7\u8535\u5eab\u5185\u3067\u81ea\u7136\u89e3\u51cd\u3057\u3066\u3044\u305f\u3060\u304f\u3053\u3068\u3092\u304a\u52e7\u3081\u3057\u307e\u3059\u3002\u3053\u306e\u65b9\u6cd5\u3067\u3059\u3068\u3001\u6642\u9593\u306f\u304b\u304b\u308a\u307e\u3059\u304c\u3001\u8089\u306e\u65e8\u5473\u6210\u5206\u306e\u6d41\u51fa\u304c\u6291\u3048\u3089\u308c\u3001\u3088\u308a\u7f8e\u5473\u3057\u304f\u304a\u53ec\u3057\u4e0a\u304c\u308a\u3044\u305f\u3060\u3051\u307e\u3059\u3002<br>\n\u30fb\u8cde\u5473\u671f\u9650\u306f\u51b7\u51cd\u4fdd\u5b58\u306790\u65e5\u3054\u3056\u3044\u307e\u3059\u304c\u3001\u304a\u5c4a\u3051\u76f4\u5f8c\u306f\u7279\u306b\u7f8e\u5473\u3057\u304f\u5473\u308f\u3063\u3066\u3044\u305f\u3060\u3051\u307e\u3059\u306e\u3067\u3001\u65e9\u3081\u306e\u8abf\u7406\u3092\u304a\u5968\u3081\u3044\u305f\u3057\u307e\u3059\u3002<br>\n<br>\n\u203b\u753b\u50cf\u306f\u304a\u5c4a\u3051\u30a4\u30e1\u30fc\u30b8\u3067\u3059\u3002<br>\n<img src=\"https:\/\/img21.shop-pro.jp\/PA01437\/442\/etc\/resize_3004.jpg?cmsp_timestamp=20200107231231\" alt=\"\" style=\"float:left;\"><br style=\"clear:both;\">",
		"init_num": "1",
		"soldout_flg": 0,
		"hide_flg": false,
		"login_sale_flg": 0,
		"info": "カートに入れるための情報",
		"gift_ng_status": null,
		"postage": "個別送料",
		"password_field": ""
	},
	"otherimg_num": 4,
	"otherimg": [
		{
			"url": "https://img07.shop-pro.jp/PA01437/442/product/146272783_o1.jpg"
		},
		{
			"url": "https://img07.shop-pro.jp/PA01437/442/product/146272783_o2.jpg"
		},
		{
			"url": "https://img07.shop-pro.jp/PA01437/442/product/146272783_o1.jpg"
		},
		{
			"url": "https://img07.shop-pro.jp/PA01437/442/product/146272783_o1.jpg"
		}
	],
	"option": [
		{
			"id": "1",
			"name": "がばいソース",
			"select_name": "付ける"
		}
	],
	"option_value": [
		{
			"id": [
				1,
				2
			],
			"name": [
				"付けない",
				"付ける"
			],
			"bid": [
				"bid-1",
				"bid-2"
			],
			"sid": [
				"sid-1",
				"sid-2"
			]
		},
		{
			"id": "1",
			"name": "付ける",
			"bid": "オプションID（オプションのリストのid）",
			"sid": "各オプション値のID"
		},
		{
			"id": "オプション詳細ID",
			"name": "各オプションの名称",
			"bid": "オプションID（オプションのリストのid）",
			"sid": "各オプション値のID"
		},
		{
			"id": "オプション詳細ID",
			"name": "各オプションの名称",
			"bid": "オプションID（オプションのリストのid）",
			"sid": "各オプション値のID"
		},
		{
			"id": "オプション詳細ID",
			"name": "各オプションの名称",
			"bid": "オプションID（オプションのリストのid）",
			"sid": "各オプション値のID"
		}
	],
	"option_price": {
		"max": "18,800円(税込)",
		"min": "18,800円(税込)",
		"max_regular": "オプションの最大の通常販売価格（割引前の販売価格）",
		"min_regular": "オプションの最小の通常販売価格（割引前の販売価格）",
		"max_members": "オプションの最大の会員価格",
		"min_members": "オプションの最小の会員価格"
	},
	"together_product_num": "商品個数",
	"together_product": [
		{
			"id": "146272783",
			"model": "",
			"name": "【九州産黒毛和牛】 ヒレステーキ600g(120g×5枚)",
			"cut_name": "【九州産黒毛和牛】 ヒレステー",
			"teika": "",
			"teika_disp": false,
			"price": 18800,
			"regular_price": 18800,
			"members_price": 18800,
			"discount_flg": false,
			"discount_rate": "",
			"shoppoint": "100",
			"link_url": "./?p=product",
			"img_url": "https://img07.shop-pro.jp/PA01437/442/product/146272783_th.jpg",
			"large_img_url": "https://img07.shop-pro.jp/PA01437/442/product/146272783.jpg",
			"soldout_flg": 0,
			"s_expl": "商品簡易説明",
			"option_price": {
				"max": 19300,
				"min": 18800,
				"max_regular": 19300,
				"min_regular": 18800,
				"max_members": 19300,
				"min_members": 18800
			}
		},
		{
			"id": "146272783",
			"model": "",
			"name": "【九州産黒毛和牛】 ヒレステーキ600g(120g×5枚)",
			"cut_name": "【九州産黒毛和牛】 ヒレステー",
			"teika": "",
			"teika_disp": false,
			"price": 18800,
			"regular_price": 18800,
			"members_price": 18800,
			"discount_flg": false,
			"discount_rate": "",
			"shoppoint": "100",
			"link_url": "./?p=product",
			"img_url": "https://img07.shop-pro.jp/PA01437/442/product/146272783_th.jpg",
			"large_img_url": "https://img07.shop-pro.jp/PA01437/442/product/146272783.jpg",
			"soldout_flg": 0,
			"s_expl": "商品簡易説明",
			"option_price": {
				"max": 19300,
				"min": 18800,
				"max_regular": 19300,
				"min_regular": 18800,
				"max_members": 19300,
				"min_members": 18800
			}
		},
		{
			"id": "146272783",
			"model": "",
			"name": "【九州産黒毛和牛】 ヒレステーキ600g(120g×5枚)",
			"cut_name": "【九州産黒毛和牛】 ヒレステー",
			"teika": "",
			"teika_disp": false,
			"price": 18800,
			"regular_price": 18800,
			"members_price": 18800,
			"discount_flg": false,
			"discount_rate": "",
			"shoppoint": "100",
			"link_url": "./?p=product",
			"img_url": "https://img07.shop-pro.jp/PA01437/442/product/146272783_th.jpg",
			"large_img_url": "https://img07.shop-pro.jp/PA01437/442/product/146272783.jpg",
			"soldout_flg": 0,
			"s_expl": "商品簡易説明",
			"option_price": {
				"max": 19300,
				"min": 18800,
				"max_regular": 19300,
				"min_regular": 18800,
				"max_members": 19300,
				"min_members": 18800
			}
		}
	],
	"option_table": "オプション表を表示※2012/07/03追加※PCテンプレートでのオプション表示に使用しています。",
	"option_view_data": "オプション表を表示※2011/05/10追加※スマートフォンテンプレートでのオプション表示に使用しています。",
	"review_use_flg": "レビュー機能の使用フラグ",
	"review_lst_url": "レビュー閲覧画面へのリンク",
	"review_send_url": "レビュー投稿画面へのリンク",
	"review_item_num": "投稿されたレビューの数",
	"reviewlist": [
		{
			"id": "レビューID",
			"nickname": "投稿者ニックネーム",
			"sex": "性別",
			"nendai": "年代",
			"star": "評価数（星の画像ではなく数値が出力されます。）",
			"title": "レビュータイトル",
			"comment": "レビュー内容",
			"img_url": "投稿画像URL",
			"date": "投稿日時",
			"res_comment": "ショップからの返信（返信がある場合のみ出力されます。）",
			"res_date": "ショップからの返信日時（返信がある場合のみ出力されます。）"
		},
		{
			"id": "レビューID",
			"nickname": "投稿者ニックネーム",
			"sex": "性別",
			"nendai": "年代",
			"star": "評価数（星の画像ではなく数値が出力されます。）",
			"title": "レビュータイトル",
			"comment": "レビュー内容",
			"img_url": "投稿画像URL",
			"date": "投稿日時",
			"res_comment": "ショップからの返信（返信がある場合のみ出力されます。）",
			"res_date": "ショップからの返信日時（返信がある場合のみ出力されます。）"
		},
		{
			"id": "レビューID",
			"nickname": "投稿者ニックネーム",
			"sex": "性別",
			"nendai": "年代",
			"star": "評価数（星の画像ではなく数値が出力されます。）",
			"title": "レビュータイトル",
			"comment": "レビュー内容",
			"img_url": "投稿画像URL",
			"date": "投稿日時",
			"res_comment": "ショップからの返信（返信がある場合のみ出力されます。）",
			"res_date": "ショップからの返信日時（返信がある場合のみ出力されます。）"
		},
		{
			"id": "レビューID",
			"nickname": "投稿者ニックネーム",
			"sex": "性別",
			"nendai": "年代",
			"star": "評価数（星の画像ではなく数値が出力されます。）",
			"title": "レビュータイトル",
			"comment": "レビュー内容",
			"img_url": "投稿画像URL",
			"date": "投稿日時",
			"res_comment": "ショップからの返信（返信がある場合のみ出力されます。）",
			"res_date": "ショップからの返信日時（返信がある場合のみ出力されます。）"
		}
	],
	"review_star_num": "評価数の上限値",
	"group_breadcrumb_list": "パンくずのリスト",
	"group_breadcrumb": [
		{
			"link_url": "グループURL",
			"name": "グループ名称"
		},
		{
			"link_url": "グループURL",
			"name": "グループ名称"
		},
		{
			"link_url": "グループURL",
			"name": "グループ名称"
		}
	],
	"subcategory_num": "4",
	"sub_category": {
		"2543763": [
			{
				"link_url": "https://www.saga-ishimaru.co.jp/?mode=cate&cbid=2543763&csid=1",
				"img_url": "サブカテゴリー画像のURL",
				"name": "ヒレ"
			},
			{
				"link_url": "https://www.saga-ishimaru.co.jp/?mode=cate&cbid=2543763&csid=2",
				"img_url": "サブカテゴリー画像のURL",
				"name": "ロース"
			},
			{
				"link_url": "https://www.saga-ishimaru.co.jp/?mode=cate&cbid=2543763&csid=3",
				"img_url": "サブカテゴリー画像のURL",
				"name": "小間切れ"
			},
			{
				"link_url": "https://www.saga-ishimaru.co.jp/?mode=cate&cbid=2543763&csid=4",
				"img_url": "サブカテゴリー画像のURL",
				"name": "赤身"
			},
			{
				"link_url": "https://www.saga-ishimaru.co.jp/?mode=cate&cbid=2543763&csid=5",
				"img_url": "サブカテゴリー画像のURL",
				"name": "肩スライス"
			},
			{
				"link_url": "https://www.saga-ishimaru.co.jp/?mode=cate&cbid=2543763&csid=6",
				"img_url": "サブカテゴリー画像のURL",
				"name": "モモスライス"
			}
		],
		"2547504": [
			{
				"link_url": "https://www.saga-ishimaru.co.jp/?mode=cate&cbid=2547504&csid=1",
				"img_url": "サブカテゴリー画像のURL",
				"name": "ヒレ"
			},
			{
				"link_url": "https://www.saga-ishimaru.co.jp/?mode=cate&cbid=2547504&csid=2",
				"img_url": "サブカテゴリー画像のURL",
				"name": "ロース"
			},
			{
				"link_url": "https://www.saga-ishimaru.co.jp/?mode=cate&cbid=2547504&csid=4",
				"img_url": "サブカテゴリー画像のURL",
				"name": "赤身"
			},
			{
				"link_url": "https://www.saga-ishimaru.co.jp/?mode=cate&cbid=2547504&csid=5",
				"img_url": "サブカテゴリー画像のURL",
				"name": "肩スライス"
			},
			{
				"link_url": "https://www.saga-ishimaru.co.jp/?mode=cate&cbid=2543763&csid=6",
				"img_url": "サブカテゴリー画像のURL",
				"name": "モモスライス"
			}
		],
		"2": [
			{
				"link_url": "サブカテゴリー別商品一覧のURL",
				"img_url": "サブカテゴリー画像のURL",
				"name": "サブカテゴリー名称1"
			},
			{
				"link_url": "サブカテゴリー別商品一覧のURL",
				"img_url": "サブカテゴリー画像のURL",
				"name": "サブカテゴリー名称2"
			},
			{
				"link_url": "サブカテゴリー別商品一覧のURL",
				"img_url": "サブカテゴリー画像のURL",
				"name": "サブカテゴリー名称3"
			}
		],
		"3": [
			{
				"link_url": "サブカテゴリー別商品一覧のURL",
				"img_url": "サブカテゴリー画像のURL",
				"name": "サブカテゴリー名称1"
			},
			{
				"link_url": "サブカテゴリー別商品一覧のURL",
				"img_url": "サブカテゴリー画像のURL",
				"name": "サブカテゴリー名称2"
			},
			{
				"link_url": "サブカテゴリー別商品一覧のURL",
				"img_url": "サブカテゴリー画像のURL",
				"name": "サブカテゴリー名称3"
			}
		],
		"4": [
			{
				"link_url": "サブカテゴリー別商品一覧のURL",
				"img_url": "サブカテゴリー画像のURL",
				"name": "サブカテゴリー名称1"
			},
			{
				"link_url": "サブカテゴリー別商品一覧のURL",
				"img_url": "サブカテゴリー画像のURL",
				"name": "サブカテゴリー名称2"
			},
			{
				"link_url": "サブカテゴリー別商品一覧のURL",
				"img_url": "サブカテゴリー画像のURL",
				"name": "サブカテゴリー名称3"
			}
		]
	},
	"subgroup_num": "6",
	"sub_group": [
		{
			"link_url": "下位グループ別商品一覧のURL",
			"img_url": "下位グループ画像のURL",
			"name": "ヒレ"
		},
		{
			"link_url": "下位グループ別商品一覧のURL",
			"img_url": "下位グループ画像のURL",
			"name": "ロース"
		},
		{
			"link_url": "下位グループ別商品一覧のURL",
			"img_url": "下位グループ画像のURL",
			"name": "ウデ"
		},
		{
			"link_url": "下位グループ別商品一覧のURL",
			"img_url": "下位グループ画像のURL",
			"name": "モモ"
		}
	],
	"category_desc_1": "大カテゴリー一覧ページのフリースペース１ ※2012/11/09追加",
	"category_desc_2": "大カテゴリー一覧ページのフリースペース２ ※2012/11/09追加",
	"subcategory_desc_1": "小カテゴリー一覧ページのフリースペース１ ※2012/11/09追加",
	"subcategory_desc_2": "小カテゴリー一覧ページのフリースペース２ ※2012/11/09追加",
	"group_desc_1": "グループページのフリースペース１ ※2012/11/09追加",
	"group_desc_2": "グループページのフリースペース２ ※2012/11/09追加",
	"search_category": "検索カテゴリー名称",
	"search_keyword": "検索文字",
	"productlist_num": "10",
	"productlist_snum": "表示されている商品の始まり",
	"productlist_enum": "表示されている商品の終わり",
	"productlist": [
		{
			"id": "146272783",
			"model": "",
			"name": "【九州産黒毛和牛】 ヒレステーキ600g(120g×5枚)",
			"cut_name": "【九州産黒毛和牛】 ヒレステー",
			"teika": "",
			"teika_disp": false,
			"price": 18800,
			"regular_price": 18800,
			"members_price": 18800,
			"discount_flg": false,
			"discount_rate": "",
			"shoppoint": "100",
			"link_url": "./?p=product",
			"img_url": "https://img07.shop-pro.jp/PA01437/442/product/146272783_th.jpg",
			"large_img_url": "https://img07.shop-pro.jp/PA01437/442/product/146272783.jpg",
			"soldout_flg": 0,
			"s_expl": "商品簡易説明",
			"option_price": {
				"max": 19300,
				"min": 18800,
				"max_regular": 19300,
				"min_regular": 18800,
				"max_members": 19300,
				"min_members": 18800
			}
		},
		{
			"id": "146272783",
			"model": "",
			"name": "【九州産黒毛和牛】 ヒレステーキ600g(120g×5枚)",
			"cut_name": "【九州産黒毛和牛】 ヒレステー",
			"teika": "",
			"teika_disp": false,
			"price": 18800,
			"regular_price": 18800,
			"members_price": 18800,
			"discount_flg": false,
			"discount_rate": "",
			"shoppoint": "100",
			"link_url": "./?p=product",
			"img_url": "https://img07.shop-pro.jp/PA01437/442/product/146272783_th.jpg",
			"large_img_url": "https://img07.shop-pro.jp/PA01437/442/product/146272783.jpg",
			"soldout_flg": 0,
			"s_expl": "商品簡易説明",
			"option_price": {
				"max": 19300,
				"min": 18800,
				"max_regular": 19300,
				"min_regular": 18800,
				"max_members": 19300,
				"min_members": 18800
			}
		},
		{
			"id": "146272783",
			"model": "",
			"name": "【九州産黒毛和牛】 ヒレステーキ600g(120g×5枚)",
			"cut_name": "【九州産黒毛和牛】 ヒレステー",
			"teika": "",
			"teika_disp": false,
			"price": 18800,
			"regular_price": 18800,
			"members_price": 18800,
			"discount_flg": false,
			"discount_rate": "",
			"shoppoint": "100",
			"link_url": "./?p=product",
			"img_url": "https://img07.shop-pro.jp/PA01437/442/product/146272783_th.jpg",
			"large_img_url": "https://img07.shop-pro.jp/PA01437/442/product/146272783.jpg",
			"soldout_flg": 0,
			"s_expl": "商品簡易説明",
			"option_price": {
				"max": 19300,
				"min": 18800,
				"max_regular": 19300,
				"min_regular": 18800,
				"max_members": 19300,
				"min_members": 18800
			}
		},
		{
			"id": "146272783",
			"model": "",
			"name": "【九州産黒毛和牛】 ヒレステーキ600g(120g×5枚)",
			"cut_name": "【九州産黒毛和牛】 ヒレステー",
			"teika": "",
			"teika_disp": false,
			"price": 18800,
			"regular_price": 18800,
			"members_price": 18800,
			"discount_flg": false,
			"discount_rate": "",
			"shoppoint": "100",
			"link_url": "./?p=product",
			"img_url": "https://img07.shop-pro.jp/PA01437/442/product/146272783_th.jpg",
			"large_img_url": "https://img07.shop-pro.jp/PA01437/442/product/146272783.jpg",
			"soldout_flg": 0,
			"s_expl": "商品簡易説明",
			"option_price": {
				"max": 19300,
				"min": 18800,
				"max_regular": 19300,
				"min_regular": 18800,
				"max_members": 19300,
				"min_members": 18800
			}
		},
		{
			"id": "146272783",
			"model": "",
			"name": "【九州産黒毛和牛】 ヒレステーキ600g(120g×5枚)",
			"cut_name": "【九州産黒毛和牛】 ヒレステー",
			"teika": "",
			"teika_disp": false,
			"price": 18800,
			"regular_price": 18800,
			"members_price": 18800,
			"discount_flg": false,
			"discount_rate": "",
			"shoppoint": "100",
			"link_url": "./?p=product",
			"img_url": "https://img07.shop-pro.jp/PA01437/442/product/146272783_th.jpg",
			"large_img_url": "https://img07.shop-pro.jp/PA01437/442/product/146272783.jpg",
			"soldout_flg": 0,
			"s_expl": "商品簡易説明",
			"option_price": {
				"max": 19300,
				"min": 18800,
				"max_regular": 19300,
				"min_regular": 18800,
				"max_members": 19300,
				"min_members": 18800
			}
		},
		{
			"id": "146272783",
			"model": "",
			"name": "【九州産黒毛和牛】 ヒレステーキ600g(120g×5枚)",
			"cut_name": "【九州産黒毛和牛】 ヒレステー",
			"teika": "",
			"teika_disp": false,
			"price": 18800,
			"regular_price": 18800,
			"members_price": 18800,
			"discount_flg": false,
			"discount_rate": "",
			"shoppoint": "100",
			"link_url": "./?p=product",
			"img_url": "https://img07.shop-pro.jp/PA01437/442/product/146272783_th.jpg",
			"large_img_url": "https://img07.shop-pro.jp/PA01437/442/product/146272783.jpg",
			"soldout_flg": 0,
			"s_expl": "商品簡易説明",
			"option_price": {
				"max": 19300,
				"min": 18800,
				"max_regular": 19300,
				"min_regular": 18800,
				"max_members": 19300,
				"min_members": 18800
			}
		},
		{
			"id": "146272783",
			"model": "",
			"name": "【九州産黒毛和牛】 ヒレステーキ600g(120g×5枚)",
			"cut_name": "【九州産黒毛和牛】 ヒレステー",
			"teika": "",
			"teika_disp": false,
			"price": 18800,
			"regular_price": 18800,
			"members_price": 18800,
			"discount_flg": false,
			"discount_rate": "",
			"shoppoint": "100",
			"link_url": "./?p=product",
			"img_url": "https://img07.shop-pro.jp/PA01437/442/product/146272783_th.jpg",
			"large_img_url": "https://img07.shop-pro.jp/PA01437/442/product/146272783.jpg",
			"soldout_flg": 0,
			"s_expl": "商品簡易説明",
			"option_price": {
				"max": 19300,
				"min": 18800,
				"max_regular": 19300,
				"min_regular": 18800,
				"max_members": 19300,
				"min_members": 18800
			}
		},
		{
			"id": "146272783",
			"model": "",
			"name": "【九州産黒毛和牛】 ヒレステーキ600g(120g×5枚)",
			"cut_name": "【九州産黒毛和牛】 ヒレステー",
			"teika": "",
			"teika_disp": false,
			"price": 18800,
			"regular_price": 18800,
			"members_price": 18800,
			"discount_flg": false,
			"discount_rate": "",
			"shoppoint": "100",
			"link_url": "./?p=product",
			"img_url": "https://img07.shop-pro.jp/PA01437/442/product/146272783_th.jpg",
			"large_img_url": "https://img07.shop-pro.jp/PA01437/442/product/146272783.jpg",
			"soldout_flg": 0,
			"s_expl": "商品簡易説明",
			"option_price": {
				"max": 19300,
				"min": 18800,
				"max_regular": 19300,
				"min_regular": 18800,
				"max_members": 19300,
				"min_members": 18800
			}
		},
		{
			"id": "146272783",
			"model": "",
			"name": "【九州産黒毛和牛】 ヒレステーキ600g(120g×5枚)",
			"cut_name": "【九州産黒毛和牛】 ヒレステー",
			"teika": "",
			"teika_disp": false,
			"price": 18800,
			"regular_price": 18800,
			"members_price": 18800,
			"discount_flg": false,
			"discount_rate": "",
			"shoppoint": "100",
			"link_url": "./?p=product",
			"img_url": "https://img07.shop-pro.jp/PA01437/442/product/146272783_th.jpg",
			"large_img_url": "https://img07.shop-pro.jp/PA01437/442/product/146272783.jpg",
			"soldout_flg": 0,
			"s_expl": "商品簡易説明",
			"option_price": {
				"max": 19300,
				"min": 18800,
				"max_regular": 19300,
				"min_regular": 18800,
				"max_members": 19300,
				"min_members": 18800
			}
		},
		{
			"id": "146272783",
			"model": "",
			"name": "【九州産黒毛和牛】 ヒレステーキ600g(120g×5枚)",
			"cut_name": "【九州産黒毛和牛】 ヒレステー",
			"teika": "",
			"teika_disp": false,
			"price": 18800,
			"regular_price": 18800,
			"members_price": 18800,
			"discount_flg": false,
			"discount_rate": "",
			"shoppoint": "100",
			"link_url": "./?p=product",
			"img_url": "https://img07.shop-pro.jp/PA01437/442/product/146272783_th.jpg",
			"large_img_url": "https://img07.shop-pro.jp/PA01437/442/product/146272783.jpg",
			"soldout_flg": 0,
			"s_expl": "商品簡易説明",
			"option_price": {
				"max": 19300,
				"min": 18800,
				"max_regular": 19300,
				"min_regular": 18800,
				"max_members": 19300,
				"min_members": 18800
			}
		}
	],
	"productlist_prev_page": "前ページへのリンクURL",
	"productlist_next_page": "次ページへのリンクURL",
	"productlist_sort_def": "おすすめ順のリンクURL（初期選択）",
	"productlist_sort_price": "価格順へのリンクURL",
	"productlist_sort_new": "新着順へのリンクURL",
	"productlist_sort_now": "現在選択中のソート（空：おすすめ、\"p\"：価格、\"n\"：新着）",
	"option_num": "オプションの個数",
	"option_item": [
		{
			"name": "名称",
			"d_flg": "在庫表示フラグ",
			"d_stk": 100,
			"price": "販売価格（ログインなし：販売価格の値を出力、ログインあり：会員価格の値を出力）",
			"regular_price": "通常販売価格（割引前の販売価格）",
			"members_price": "会員価格",
			"discount_flg": "割引フラグ（ログイン中の場合、販売価格より会員価格の方が価格が低い場合はTRUE、それ以外はFALSE）",
			"discount_rate": "割引率（○○%の形式で出力されます。割引フラグ[discount_flg]がTRUEの場合のみ出力されます。）"
		},
		{
			"name": "名称",
			"d_flg": "在庫表示フラグ",
			"d_stk": 100,
			"price": "販売価格（ログインなし：販売価格の値を出力、ログインあり：会員価格の値を出力）",
			"regular_price": "通常販売価格（割引前の販売価格）",
			"members_price": "会員価格",
			"discount_flg": "割引フラグ（ログイン中の場合、販売価格より会員価格の方が価格が低い場合はTRUE、それ以外はFALSE）",
			"discount_rate": "割引率（○○%の形式で出力されます。割引フラグ[discount_flg]がTRUEの場合のみ出力されます。）"
		},
		{
			"name": "名称",
			"d_flg": "在庫表示フラグ",
			"d_stk": 100,
			"price": "販売価格（ログインなし：販売価格の値を出力、ログインあり：会員価格の値を出力）",
			"regular_price": "通常販売価格（割引前の販売価格）",
			"members_price": "会員価格",
			"discount_flg": "割引フラグ（ログイン中の場合、販売価格より会員価格の方が価格が低い場合はTRUE、それ以外はFALSE）",
			"discount_rate": "割引率（○○%の形式で出力されます。割引フラグ[discount_flg]がTRUEの場合のみ出力されます。）"
		},
		{
			"name": "名称",
			"d_flg": "在庫表示フラグ",
			"d_stk": 100,
			"price": "販売価格（ログインなし：販売価格の値を出力、ログインあり：会員価格の値を出力）",
			"regular_price": "通常販売価格（割引前の販売価格）",
			"members_price": "会員価格",
			"discount_flg": "割引フラグ（ログイン中の場合、販売価格より会員価格の方が価格が低い場合はTRUE、それ以外はFALSE）",
			"discount_rate": "割引率（○○%の形式で出力されます。割引フラグ[discount_flg]がTRUEの場合のみ出力されます。）"
		},
		{
			"name": "名称",
			"d_flg": "在庫表示フラグ",
			"d_stk": 100,
			"price": "販売価格（ログインなし：販売価格の値を出力、ログインあり：会員価格の値を出力）",
			"regular_price": "通常販売価格（割引前の販売価格）",
			"members_price": "会員価格",
			"discount_flg": "割引フラグ（ログイン中の場合、販売価格より会員価格の方が価格が低い場合はTRUE、それ以外はFALSE）",
			"discount_rate": "割引率（○○%の形式で出力されます。割引フラグ[discount_flg]がTRUEの場合のみ出力されます。）"
		}
	],
	"privacy": [
		{
			"title": "タイトル",
			"note": "内容"
		},
		{
			"title": "タイトル",
			"note": "内容"
		},
		{
			"title": "タイトル",
			"note": "内容"
		},
		{
			"title": "タイトル",
			"note": "内容"
		},
		{
			"title": "タイトル",
			"note": "内容"
		}
	]
}
